rompy_schism/__init__.py
rompy_schism/bctides.py
rompy_schism/boundary.py
rompy_schism/boundary_conditions.py
rompy_schism/boundary_core.py
rompy_schism/config.py
rompy_schism/config_legacy.py
rompy_schism/config_plotting.py
rompy_schism/config_plotting_boundary.py
rompy_schism/config_plotting_tides.py
rompy_schism/data.py
rompy_schism/grid.py
rompy_schism/hotstart.py
rompy_schism/interface.py
rompy_schism/numpy_types.py
rompy_schism/tides_enhanced.py
rompy_schism/utils.py
rompy_schism/vgrid.py
rompy_schism/namelists/__init__.py
rompy_schism/namelists/basemodel.py
rompy_schism/namelists/cosine.py
rompy_schism/namelists/example_nml.py
rompy_schism/namelists/generate_models.py
rompy_schism/namelists/generate_models_llm.py
rompy_schism/namelists/generate_models_llm_sections.py
rompy_schism/namelists/generate_models_llmv2.py
rompy_schism/namelists/ice.py
rompy_schism/namelists/icm.py
rompy_schism/namelists/mice.py
rompy_schism/namelists/param.py
rompy_schism/namelists/schism.py
rompy_schism/namelists/sediment.py
rompy_schism/namelists/sflux.py
rompy_schism/namelists/wwminput.py
rompy_schism/namelists/wwminput_WW3.py
rompy_schism/namelists/wwminput_spectra.py
rompy_schism/namelists/claude_full/ice.py
rompy_schism/namelists/claude_full/icm.py
rompy_schism/namelists/claude_full/mice.py
rompy_schism/namelists/claude_full/param.py
rompy_schism/namelists/claude_full/sediment.py
rompy_schism/namelists/claude_full/wwminput_WW3.py
rompy_schism/namelists/claude_full/wwminput_spectra.py
rompy_schism/namelists/handwritten/cosine.py
rompy_schism/namelists/handwritten/ice.py
rompy_schism/namelists/handwritten/icm.py
rompy_schism/namelists/handwritten/param.py
rompy_schism/namelists/handwritten/sediment.py
rompy_schism/namelists/sample_inputs/create_model.py
rompy_schism/namelists/sample_inputs/render.py
rompy_schism/templates/schism/{{runtime.staging_dir}}/README
rompy_schism/templates/schism/{{runtime.staging_dir}}/datasets/readme.md
rompy_schism-0.6.0.dist-info/licenses/AUTHORS.rst
rompy_schism-0.6.0.dist-info/licenses/LICENSE
rompy_schism-0.6.0.dist-info/licenses/NOTICE
rompy_schism-0.6.0.dist-info/METADATA
rompy_schism-0.6.0.dist-info/WHEEL
rompy_schism-0.6.0.dist-info/entry_points.txt
rompy_schism-0.6.0.dist-info/top_level.txt
rompy_schism-0.6.0.dist-info/RECORD
