Metadata-Version: 2.4
Name: rompy-schism
Version: 0.6.0
Summary: SCHISM model plugin for rompy
Author-email: Rompy Contributors <developers@rompy.com>
Maintainer-email: Rompy Contributors <developers@rompy.com>
License: Apache Software License 2.0
Project-URL: bugs, https://github.com/rom-py/rompy-schism/issues
Project-URL: changelog, https://github.com/rom-py/rompy-schism/blob/master/changelog.md
Project-URL: homepage, https://github.com/rom-py/rompy-schism
Classifier: Development Status :: 3 - Alpha
Classifier: Intended Audience :: Science/Research
Classifier: License :: OSI Approved :: Apache Software License
Classifier: Natural Language :: English
Classifier: Operating System :: OS Independent
Classifier: Topic :: Scientific/Engineering
Classifier: Topic :: Scientific/Engineering :: Physics
Classifier: Programming Language :: Python :: 3
Classifier: Programming Language :: Python :: 3.10
Classifier: Programming Language :: Python :: 3.11
Classifier: Programming Language :: Python :: 3.12
Requires-Python: >=3.10
License-File: LICENSE
License-File: NOTICE
License-File: AUTHORS.rst
Requires-Dist: rompy>=0.6
Requires-Dist: pydantic>2
Requires-Dist: pylibs-ocean
Requires-Dist: pytmd
Provides-Extra: dev
Requires-Dist: coverage; extra == "dev"
Requires-Dist: mypy; extra == "dev"
Requires-Dist: pytest; extra == "dev"
Requires-Dist: ruff; extra == "dev"
Requires-Dist: requests; extra == "dev"
Provides-Extra: test
Requires-Dist: pytest; extra == "test"
Requires-Dist: coverage; extra == "test"
Requires-Dist: requests; extra == "test"
Provides-Extra: docs
Requires-Dist: autodoc_pydantic; extra == "docs"
Requires-Dist: ipython; extra == "docs"
Requires-Dist: nbsphinx; extra == "docs"
Requires-Dist: pydata_sphinx_theme; extra == "docs"
Requires-Dist: sphinx<7.3.6; extra == "docs"
Requires-Dist: sphinx-collections; extra == "docs"
Dynamic: license-file
